depl/__init__.py
depl/depl.py
depl-0.1.dev1.dist-info/METADATA
depl-0.1.dev1.dist-info/WHEEL
depl-0.1.dev1.dist-info/entry_points.txt
depl-0.1.dev1.dist-info/top_level.txt
depl-0.1.dev1.dist-info/RECORD
