Metadata-Version: 2.1
Name: depl
Version: 0.1.dev1
Summary: Super easy remote compute management
Home-page: https://github.com/aaronsgithub/depl
Author: Aaron Ghani
Author-email: sendaaronstuff@outlook.com
License: UNKNOWN
Platform: UNKNOWN
Requires-Python: >=3.8
